beamshapy/BeamShaper.py
beamshapy/__init__.py
beamshapy/amplitude_generation/AmplitudeGenerator.py
beamshapy/amplitude_generation/__init__.py
beamshapy/helpers.py
beamshapy/intensity_generation/IntensityGenerator.py
beamshapy/intensity_generation/__init__.py
beamshapy/intensity_generation/functions_Gerchberg_Saxton.py
beamshapy/intensity_generation/functions_intensity_profile.py
beamshapy/mask_generation/MaskGenerator.py
beamshapy/mask_generation/__init__.py
beamshapy/mask_generation/functions_masks_generation.py
beamshapy/spatial_profiles/__init__.py
beamshapy/spatial_profiles/functions_basic_shapes.py
beamshapy-0.1.13.dist-info/METADATA
beamshapy-0.1.13.dist-info/WHEEL
beamshapy-0.1.13.dist-info/RECORD
